MANIFEST.in
README.rst
epeg.py
setup.py
epeg_cffi.egg-info/PKG-INFO
epeg_cffi.egg-info/SOURCES.txt
epeg_cffi.egg-info/dependency_links.txt
epeg_cffi.egg-info/requires.txt
epeg_cffi.egg-info/top_level.txt
src/Epeg.h
src/epeg.c
src/epeg_private.h