Metadata-Version: 1.0
Name: epeg-cffi
Version: 0.02
Summary: Insanely fast JPEG/ JPG thumbnail scaling with the minimum fuss and CPU overhead. It makes use of libjpeg features of being able to load an image by only decoding the DCT coefficients needed to reconstruct an image of the size desired.
Home-page: http://github.com/jbaiter/epeg-cffi.git
Author: Johannes Baiter
Author-email: johannes.baiter@gmail.com
License: MIT
Platform: UNKNOWN
